.gitignore
MANIFEST.in
README.rst
setup.cfg
setup.py
docs/HISTORY.txt
docs/LICENSE.GPL
docs/LICENSE.txt
docs/MANUAL.txt
raptus/__init__.py
raptus.article.alias.egg-info/PKG-INFO
raptus.article.alias.egg-info/SOURCES.txt
raptus.article.alias.egg-info/dependency_links.txt
raptus.article.alias.egg-info/entry_points.txt
raptus.article.alias.egg-info/namespace_packages.txt
raptus.article.alias.egg-info/not-zip-safe
raptus.article.alias.egg-info/requires.txt
raptus.article.alias.egg-info/top_level.txt
raptus/article/__init__.py
raptus/article/alias/__init__.py
raptus/article/alias/allcontent.zcml
raptus/article/alias/base.py
raptus/article/alias/collections.py
raptus/article/alias/collections.zcml
raptus/article/alias/config.py
raptus/article/alias/configure.zcml
raptus/article/alias/contentfader.zcml
raptus/article/alias/contentflow.zcml
raptus/article/alias/contentswitcher.zcml
raptus/article/alias/fader.zcml
raptus/article/alias/files.py
raptus/article/alias/flash.py
raptus/article/alias/flash.zcml
raptus/article/alias/form.py
raptus/article/alias/gallery.zcml
raptus/article/alias/images.py
raptus/article/alias/index.py
raptus/article/alias/interfaces.py
raptus/article/alias/lightbox.zcml
raptus/article/alias/lightboxgallery.zcml
raptus/article/alias/links.py
raptus/article/alias/listings.zcml
raptus/article/alias/manageable.py
raptus/article/alias/maps.py
raptus/article/alias/maps.zcml
raptus/article/alias/media.py
raptus/article/alias/media.zcml
raptus/article/alias/nesting.py
raptus/article/alias/overrides.zcml
raptus/article/alias/permissions.zcml
raptus/article/alias/randomcontent.zcml
raptus/article/alias/randomimage.zcml
raptus/article/alias/slider.zcml
raptus/article/alias/subscribers.py
raptus/article/alias/table.py
raptus/article/alias/table.zcml
raptus/article/alias/browser/__init__.py
raptus/article/alias/browser/alias_icon.gif
raptus/article/alias/browser/configure.zcml
raptus/article/alias/browser/view.pt
raptus/article/alias/browser/view.py
raptus/article/alias/content/__init__.py
raptus/article/alias/content/alias.py
raptus/article/alias/content/configure.zcml
raptus/article/alias/profiles/default/factorytool.xml
raptus/article/alias/profiles/default/metadata.xml
raptus/article/alias/profiles/default/propertiestool.xml
raptus/article/alias/profiles/default/rolemap.xml
