Metadata-Version: 1.1
Name: raptus.article.alias
Version: 1.0a4
Summary: Provides the possibility to create aliases for content objects which may be contained in an article and display them in the specified components
Home-page: https://github.com/Raptus/raptus.article.alias
Author: Raptus AG
Author-email: dev@raptus.com
License: GPL
Platform: UNKNOWN
Classifier: Programming Language :: Python
Classifier: Topic :: Software Development :: Libraries :: Python Modules
